odoo/addons/picking_very_high_priority_mrp/README.rst
odoo/addons/picking_very_high_priority_mrp/__init__.py
odoo/addons/picking_very_high_priority_mrp/__manifest__.py
odoo/addons/picking_very_high_priority_mrp/i18n/es.po
odoo/addons/picking_very_high_priority_mrp/models/__init__.py
odoo/addons/picking_very_high_priority_mrp/models/mrp_production.py
odoo/addons/picking_very_high_priority_mrp/static/description/icon.png
odoo_addon_picking_very_high_priority_mrp-15.0.1.0.0.2.dist-info/METADATA
odoo_addon_picking_very_high_priority_mrp-15.0.1.0.0.2.dist-info/WHEEL
odoo_addon_picking_very_high_priority_mrp-15.0.1.0.0.2.dist-info/top_level.txt
odoo_addon_picking_very_high_priority_mrp-15.0.1.0.0.2.dist-info/RECORD
